transcribe_align_textgrid/__init__.py
transcribe_align_textgrid/__main__.py
transcribe_align_textgrid/adapter.py
transcribe_align_textgrid/cli.py
transcribe_align_textgrid/whisper_schema.py
transcribe_align_textgrid-0.2.5.dist-info/licenses/LICENCE
transcribe_align_textgrid-0.2.5.dist-info/METADATA
transcribe_align_textgrid-0.2.5.dist-info/WHEEL
transcribe_align_textgrid-0.2.5.dist-info/top_level.txt
transcribe_align_textgrid-0.2.5.dist-info/RECORD
