Metadata-Version: 2.4
Name: transcribe_align_textgrid
Version: 0.2.5
Summary: Create for-aligned transcription TextGrids from Audio
Author-email: JJWRoeloffs <jelleroeloffs@gmail.com>
License:                     GNU AFFERO GENERAL PUBLIC LICENSE
Project-URL: Homepage, https://github.com/JJWRoeloffs/transcribe_align_textgrid
Project-URL: Bug Tracker, https://github.com/JJWRoeloffs/transcribe_align_textgrid/issues
Keywords: praat,whisper,force-align,TextGrid
Classifier: Programming Language :: Python :: 3
Classifier: License :: OSI Approved :: GNU Affero General Public License v3
Classifier: Development Status :: 5 - Production/Stable
Classifier: Intended Audience :: Science/Research
Classifier: Operating System :: OS Independent
Requires-Python: >=3.9
License-File: LICENCE
Requires-Dist: praatio~=6.2
Requires-Dist: jsonschema~=4.23
Requires-Dist: whisper-timestamped~=1.15
Provides-Extra: dev
Requires-Dist: pytest; extra == "dev"
Requires-Dist: pytest-cov; extra == "dev"
Requires-Dist: black; extra == "dev"
Dynamic: license-file
